{
    "modules" :
    [
        {
            "module name" : "logger_hl",
            "module path" : "..\\..\\..\\modules\\logger\\Debug\\logger_hl.dll",
            "args" : {"filename":"C:\\Temp\\Log.txt"}
        },
        {
          "module name": "hello_world",
          "module path": "..\\..\\..\\modules\\hello_world\\Debug\\hello_world_hl.dll",
          "args": null
        },
        {
            "module name" : "dotnet_hello_world",
            "module path" : "..\\..\\..\\bindings\\dotnet\\Debug\\dotnet_hl.dll",
            "args" : {
                "dotnet_module_path": "HelloWorldModule",
                "dotnet_module_entry_class": "HelloWorldModule.DotNETHelloWorld",
                "dotnet_module_args": "module configuration"
            }
        }
    ]
}
